{
    "id": 1004235,
    "organo_nivel1": "PAIPORTA",
    "organo_nivel2": "AYUNTAMIENTO DE PAIPORTA",
    "sedeElectronica": "",
    "codigoBDNS": "802675",
    "fechaRecepcion": "2024-12-12T15:32:22+01:00",
    "instrumentos": "SUBVENCIÓN Y ENTREGA DINERARIA SIN CONTRAPRESTACIÓN ",
    "tipoConvocatoria": "Concesión directa - canónica",
    "presupuestoTotal": 5300000,
    "descripcion": "AYUDAS FUNDACION AMANCIO ORTEGA - DANA",
    "tiposBeneficiarios": "PERSONAS FÍSICAS QUE NO DESARROLLAN ACTIVIDAD ECONÓMICA",
    "sectores": "ACTIVIDADES SANITARIAS Y DE SERVICIOS SOCIALES",
    "regiones": "ES523 - Valencia / València",
    "descripcionFinalidad": "Otras Prestaciones económicas",
    "descripcionBasesReguladoras": "PRESUPUESTO MUNICIPAL DEL AYUNTAMIENTO DE PAIPORTA AÑO 2024",
    "urlBasesReguladoras": "https://bop.dival.es/bop/downloads?anuncioNumReg=2024/02806&lang=va",
    "sePublicaDiarioOficial": "Sí",
    "abierto": "No",
    "fechaInicioSolicitud": "2024-01-01T00:00:00+01:00",
    "fechaFinSolicitud": "",
    "textInicio": "Dia siguiente a la publicación de el BOP",
    "textFin": "un mes desde el dia siguiente de la publicación en el BOP",
    "reglamento": "",
    "documentos": "\nDescripción: Texto en castellano de la convocatoria, Nombre: Resolucion_N_3206_de_12122024_DECRETO_ALCALDIA_BASES_REGULADORAS_AYUDAS_FUNDACION_AMANCIO_ORTEGA_GAO.pdf, Enlace: https://www.pap.hacienda.gob.es/bdnstrans/GE/es/convocatoria/802675/document/1175893 "
}