{
    "id": 1004607,
    "organo_nivel1": "LA RIOJA",
    "organo_nivel2": "CONSEJERÍA DE AGRICULTURA, GANADERÍA, MUNDO RURAL Y MEDIO AMBIENTE",
    "sedeElectronica": "https://web.larioja.org/oficina-electronica/tramite?n=01927",
    "codigoBDNS": "803047",
    "fechaRecepcion": "2024-12-13T21:18:31+01:00",
    "instrumentos": "SUBVENCIÓN Y ENTREGA DINERARIA SIN CONTRAPRESTACIÓN ",
    "tipoConvocatoria": "Concurrencia competitiva - canónica",
    "presupuestoTotal": 9920,
    "descripcion": "A EE.LL. Parques Naturales CAR para inversiones conserv. medio nat. e infraestr",
    "tiposBeneficiarios": "PERSONAS JURÍDICAS QUE NO DESARROLLAN ACTIVIDAD ECONÓMICA",
    "sectores": " Silvicultura y explotación forestal",
    "regiones": "ES230 - La Rioja",
    "descripcionFinalidad": "Infraestructuras",
    "descripcionBasesReguladoras": "Bases reguladoras para la concesión de subvenciones para inversiones en conservación del medio natural e infraestructuras a las entidades locales integradas en Parques Naturales declarados en la CAR",
    "urlBasesReguladoras": "https://web.larioja.org/normativa?n=2112",
    "sePublicaDiarioOficial": "Sí",
    "abierto": "No",
    "fechaInicioSolicitud": "",
    "fechaFinSolicitud": "2025-03-01T00:00:00+01:00",
    "textInicio": "Con la publicación de la convocatoria",
    "textFin": "",
    "reglamento": "",
    "documentos": "\nDescripción: Texto en castellano de la convocatoria, Nombre: Resoluci_n_inversi_n_parques_naturales__para_el_ejercicio_2025.pdf, Enlace: https://www.pap.hacienda.gob.es/bdnstrans/GE/es/convocatoria/803047/document/1176793 "
}