[
    {
        "id": 1006500,
        "mrr": false,
        "numeroConvocatoria": "804940",
        "descripcion": "Convocatoria de subvenciones para la organización de eventos deportivo-turísticos para el año 2024",
        "descripcionLeng": "Convocatoria  de subvencións para a organización de eventos deportivo-turísticos para o ano 2024",
        "fechaRecepcion": "2024-12-20T18:38:26+01:00",
        "nivel1": "PONTES DE GARCÍA RODRÍGUEZ, AS",
        "nivel2": "AYUNTAMIENTO DE AS PONTES DE GARCÍA RODRÍGUEZ",
        "nivel3": null,
        "codigoInvente": null
    },
    {
        "id": 1006440,
        "mrr": false,
        "numeroConvocatoria": "804880",
        "descripcion": "Convocatoria 2025 Apoyo a la creación escénica",
        "descripcionLeng": null,
        "fechaRecepcion": "2024-12-20T14:48:37+01:00",
        "nivel1": "SALAMANCA",
        "nivel2": "AYUNTAMIENTO DE SALAMANCA",
        "nivel3": null,
        "codigoInvente": null
    },
    {
        "id": 1006439,
        "mrr": false,
        "numeroConvocatoria": "804879",
        "descripcion": "CONVOCATORIA ORDINARIA DE AYUDAS DE EMERGENCIA SOCIAL MUNICIPALES Y PREVENCIÓN DE LA EXCLUSIÓN SOCIAL. EJERCICIO 2025",
        "descripcionLeng": null,
        "fechaRecepcion": "2024-12-20T14:48:14+01:00",
        "nivel1": "VILLANUEVA DE LA TORRE",
        "nivel2": "AYUNTAMIENTO DE VILLANUEVA DE LA TORRE",
        "nivel3": null,
        "codigoInvente": null
    },
    {
        "id": 1006433,
        "mrr": false,
        "numeroConvocatoria": "804873",
        "descripcion": "Resolución de 12 de diciembre 2024, Presidencia de la Generalitat, por la que se convocan ayudas destinadas a promover la protección, el fomento y el desarrollo del patrimonio y la dinamización cultural, y la adecuación y la renovación de bienes y espac",
        "descripcionLeng": "Resolució de 12 de desembre 2024, Presidència de la Generalitat, per la qual es convoquen ajudes destinades a promoure la protecció, el foment i el desenvolupament del patrimoni i la dinamització cultural, i l'adequació i la renovació de béns i espais",
        "fechaRecepcion": "2024-12-20T14:31:25+01:00",
        "nivel1": "COMUNITAT VALENCIANA",
        "nivel2": "SECRETARÍA AUTONÓMICA DE PRESIDENCIA",
        "nivel3": null,
        "codigoInvente": null
    },
    {
        "id": 1006430,
        "mrr": false,
        "numeroConvocatoria": "804870",
        "descripcion": "DECRETO DE LA DELEGADA DEL ÁREA DE GOBIERNO DE ECONOMÍA, INNOVACIÓN Y HACIENDA, POR EL QUE SE APRUEBA LA CONVOCATORIA PÚBLICA DE LA PRIMERA EDICIÓN DE LOS PREMIOS CONSUMO RESPONSABLE CIUDAD DE MADRID",
        "descripcionLeng": null,
        "fechaRecepcion": "2024-12-20T14:25:51+01:00",
        "nivel1": "MADRID",
        "nivel2": "ÁREA DE GOBIERNO DE ECONOMÍA, INNOVACIÓN Y HACIENDA",
        "nivel3": null,
        "codigoInvente": null
    },
    {
        "id": 1006424,
        "mrr": false,
        "numeroConvocatoria": "804864",
        "descripcion": "Convocatoria de una beca de formación para personas licenciadas o graduadas en Derecho con destino en el Servicio de Régimen Jurídico de Interior",
        "descripcionLeng": null,
        "fechaRecepcion": "2024-12-20T14:12:51+01:00",
        "nivel1": "COMUNIDAD FORAL DE NAVARRA",
        "nivel2": "DEPARTAMENTO DE INTERIOR, FUNCION PUBLICA Y JUSTICIA",
        "nivel3": null,
        "codigoInvente": null
    },
    {
        "id": 1006421,
        "mrr": false,
        "numeroConvocatoria": "804861",
        "descripcion": "RESOLUCIÓN de la directora general de Producción Agrícola y Ganadera, por la que se establece la convocatoria anticipada, para el Plan 2025, de las ayudas de la Comunitat Valenciana destinadas a la suscripción de seguros agrarios incluidos en los planes a",
        "descripcionLeng": "RESOLUCIÓ de la directora general de Producció Agrícola i Ramadera, per la qual s’establix la convocatòria anticipada, per al Pla 2025, de les ajudes de la Comunitat Valenciana destinades a la subscripció d’assegurances agràries incloses en els plans anua",
        "fechaRecepcion": "2024-12-20T14:10:35+01:00",
        "nivel1": "COMUNITAT VALENCIANA",
        "nivel2": "SECRETARÍA AUTONÓMICA DE AGRICULTURA, GANADERÍA Y PESCA",
        "nivel3": null,
        "codigoInvente": null
    },
    {
        "id": 1006420,
        "mrr": false,
        "numeroConvocatoria": "804860",
        "descripcion": "Convocatoria Ayudas Pyme Global Visita a Feria Fruit Logistica 2025",
        "descripcionLeng": null,
        "fechaRecepcion": "2024-12-20T14:10:09+01:00",
        "nivel1": "OTROS",
        "nivel2": "CÁMARA DE COMERCIO DE CAMPO DE GIBRALTAR",
        "nivel3": null,
        "codigoInvente": null
    },
    {
        "id": 1006417,
        "mrr": false,
        "numeroConvocatoria": "804857",
        "descripcion": "Convocatoria Programa Pyme Global 2025 - Visita a la feria PARIS WINE (París) para empresas de la provincia de Córdoba",
        "descripcionLeng": null,
        "fechaRecepcion": "2024-12-20T14:07:59+01:00",
        "nivel1": "OTROS",
        "nivel2": "CÁMARA DE COMERCIO DE CÓRDOBA",
        "nivel3": null,
        "codigoInvente": null
    },
    {
        "id": 1006413,
        "mrr": false,
        "numeroConvocatoria": "804853",
        "descripcion": "PLAN DE SUBVENCIONES DE  IGUALDAD DE  TODOS Y TODAS DESTINADO A MUNICIPIOS Y ENTIDADES LOCALES MENORES DE LA PROVINCIA DE ZARAGOZA EJERCICIO 2025",
        "descripcionLeng": null,
        "fechaRecepcion": "2024-12-20T14:03:32+01:00",
        "nivel1": "DIPUTACIÓN PROV. DE ZARAGOZA",
        "nivel2": "DIPUTACIÓN PROVINCIAL DE ZARAGOZA",
        "nivel3": null,
        "codigoInvente": null
    },
    {
        "id": 1006407,
        "mrr": false,
        "numeroConvocatoria": "804847",
        "descripcion": "CONVOCATORIA ANTICIPADA DE DOS BECAS DE FORMACIÓN EN COMUNICACIÓN AUDIOVISUAL. ANUALIDAD 2025.",
        "descripcionLeng": null,
        "fechaRecepcion": "2024-12-20T13:54:15+01:00",
        "nivel1": "DIPUTACIÓN PROV. DE ALICANTE",
        "nivel2": "DIPUTACIÓN PROVINCIAL DE ALACANT/ALICANTE",
        "nivel3": null,
        "codigoInvente": null
    },
    {
        "id": 1006401,
        "mrr": false,
        "numeroConvocatoria": "804841",
        "descripcion": "XV Premio de Poesía Hermanos Machado, aprobado por Resolución de la Vicepresidencia del Instituto de Cultura y Artes de Sevilla (ICAS) de fecha 19 de diciembre de 2024, del Servicio de Gestión Administrativa y Subvenciones.",
        "descripcionLeng": null,
        "fechaRecepcion": "2024-12-20T13:49:39+01:00",
        "nivel1": "SEVILLA",
        "nivel2": "AYUNTAMIENTO DE SEVILLA",
        "nivel3": null,
        "codigoInvente": null
    },
    {
        "id": 1006399,
        "mrr": false,
        "numeroConvocatoria": "804839",
        "descripcion": "BASES Y CONVOCATORIA DEL XXXVI CONCURSO DE CARTEL DEL CARNAVAL DE BORNOS 2025",
        "descripcionLeng": null,
        "fechaRecepcion": "2024-12-20T13:49:19+01:00",
        "nivel1": "BORNOS",
        "nivel2": "AYUNTAMIENTO DE BORNOS",
        "nivel3": null,
        "codigoInvente": null
    },
    {
        "id": 1006390,
        "mrr": false,
        "numeroConvocatoria": "804830",
        "descripcion": "CONVOCATORIA DE SUBVENCIONES PARA LAS FIESTAS DE BARRIO ORGANIZADAS POR ASOCIACIONES DE VECINOS. EJERCICIO PRESUPUESTARIO 2024",
        "descripcionLeng": "CONVOCATÒRIA DE SUBVENCIONS PER A LES FESTES DE BARRI ORGANITZADES PER ASSOCIACIONS DE VEÏNS. EXERCICI PRESSUPOSTARI 2024",
        "fechaRecepcion": "2024-12-20T13:43:14+01:00",
        "nivel1": "BLANES",
        "nivel2": "AYUNTAMIENTO DE BLANES",
        "nivel3": null,
        "codigoInvente": null
    },
    {
        "id": 1006378,
        "mrr": false,
        "numeroConvocatoria": "804818",
        "descripcion": "CONVOCATORIA PYME GLOBAL 2025. VISITA A FERIA GULFOOD 2025 DUBAI. AYUDAS PARA EMPRESAS DE LA DEMARCACIÓN TERRITORIAL DE LA CÁMARA DE COMERCIO DE GRANADA",
        "descripcionLeng": null,
        "fechaRecepcion": "2024-12-20T13:29:53+01:00",
        "nivel1": "OTROS",
        "nivel2": "CÁMARA DE COMERCIO DE GRANADA",
        "nivel3": null,
        "codigoInvente": null
    },
    {
        "id": 1006365,
        "mrr": false,
        "numeroConvocatoria": "804805",
        "descripcion": "Resolución de 12 de diciembre 2024, de la Presidencia de la Generalitat, por la que se convocan ayudas destinadas a municipios y entidades locales menores de la Comunitat Valenciana con población que no exceda de 50.000 habitantes, para financiar actuacio",
        "descripcionLeng": "Resolució de 12de desembre 2024, de la Presidència de la Generalitat, per la qual es convoquen ajudes destinades a municipis i entitats locals menors de la Comunitat Valenciana amb població que no excedisca de 50.000 habitants, per a finançar actuacions",
        "fechaRecepcion": "2024-12-20T13:19:04+01:00",
        "nivel1": "COMUNITAT VALENCIANA",
        "nivel2": "SECRETARÍA AUTONÓMICA DE PRESIDENCIA",
        "nivel3": null,
        "codigoInvente": null
    },
    {
        "id": 1006363,
        "mrr": false,
        "numeroConvocatoria": "804803",
        "descripcion": "CONVOCATORIA ANTICIPADA DE UNA BECA DE FORMACIÓN PARA GRADOS EN DOCUMENTACIÓN O EN INFORMACIÓN Y DOCUMENTACIÓN. ANUALIDAD 2025",
        "descripcionLeng": null,
        "fechaRecepcion": "2024-12-20T13:17:43+01:00",
        "nivel1": "DIPUTACIÓN PROV. DE ALICANTE",
        "nivel2": "DIPUTACIÓN PROVINCIAL DE ALACANT/ALICANTE",
        "nivel3": null,
        "codigoInvente": null
    },
    {
        "id": 1006359,
        "mrr": false,
        "numeroConvocatoria": "804799",
        "descripcion": "Resolución de 20 de diciembre de 2024, del Servicio Público de Empleo de Castilla y León, por la que se convocan becas y ayudas para personas desempleadas que participen en la oferta formativa prevista en la Orden TMS/368/2019, de 28 de marzo",
        "descripcionLeng": null,
        "fechaRecepcion": "2024-12-20T13:15:23+01:00",
        "nivel1": "CASTILLA Y LEÓN",
        "nivel2": "SERVICIO PÚBLICO DE EMPLEO DE CASTILLA Y LEÓN",
        "nivel3": null,
        "codigoInvente": null
    },
    {
        "id": 1006355,
        "mrr": false,
        "numeroConvocatoria": "804795",
        "descripcion": "Acuerdo de Junta de Gobierno Local de 13-12-2024 por el que se convoca la Concesión de Ayudas a Escolares de Alcalá de Henares con necesidades de material didáctico, para el Curso 2024-2025",
        "descripcionLeng": null,
        "fechaRecepcion": "2024-12-20T13:12:05+01:00",
        "nivel1": "ALCALÁ DE HENARES",
        "nivel2": "AYUNTAMIENTO DE ALCALÁ DE HENARES",
        "nivel3": null,
        "codigoInvente": null
    },
    {
        "id": 1006343,
        "mrr": false,
        "numeroConvocatoria": "804783",
        "descripcion": "CONVOCATORIA PYME GLOBAL 2025 VISITA A FERIA FRUITLOGISTICA 2025. BERLIN (ALEMANIA). DEL 5 AL 7 DE FEBRERO DE 2025. PARA PYMES DE LA DEMARCACIÓN TERRITORIAL DE LA CÁMARA DE COMERCIO DE GRANADA.",
        "descripcionLeng": null,
        "fechaRecepcion": "2024-12-20T13:06:40+01:00",
        "nivel1": "OTROS",
        "nivel2": "CÁMARA DE COMERCIO DE GRANADA",
        "nivel3": null,
        "codigoInvente": null
    },
    {
        "id": 1006342,
        "mrr": false,
        "numeroConvocatoria": "804782",
        "descripcion": "AYUDAS ECONOMICAS ORGANIZACION ACTIVIDADES DEPORTIVAS CARACTER NACIONAL 1º SEMESTRE ",
        "descripcionLeng": null,
        "fechaRecepcion": "2024-12-20T13:06:02+01:00",
        "nivel1": "ZARAGOZA",
        "nivel2": "ZARAGOZA DEPORTE, S.A.",
        "nivel3": null,
        "codigoInvente": "INV00005459"
    },
    {
        "id": 1006331,
        "mrr": false,
        "numeroConvocatoria": "804771",
        "descripcion": "Resolución SOD/INVES/24/24/02, de 20 de diciembre de 2024, por la que se convoca para el año 2024 la línea de subvenciones del programa de “Fomento de la transferencia tecnológica (INVESNOVA)”.",
        "descripcionLeng": null,
        "fechaRecepcion": "2024-12-20T12:53:22+01:00",
        "nivel1": "CANTABRIA",
        "nivel2": "SOCIEDAD PARA EL DESARROLLO REGIONAL DE CANTABRIA, S.A.",
        "nivel3": null,
        "codigoInvente": "INV00005144"
    },
    {
        "id": 1006324,
        "mrr": false,
        "numeroConvocatoria": "804764",
        "descripcion": "Acuerdo de Junta de Gobierno Local 13-12-2024 por el que se convoca la Concesión de ayudas a Escolares de Alcalá de Henares para el Desarrollo de Actividades complementarias promovidas por sus Centros Docentes, Curso 2024-2025.",
        "descripcionLeng": null,
        "fechaRecepcion": "2024-12-20T12:44:57+01:00",
        "nivel1": "ALCALÁ DE HENARES",
        "nivel2": "AYUNTAMIENTO DE ALCALÁ DE HENARES",
        "nivel3": null,
        "codigoInvente": null
    },
    {
        "id": 1006305,
        "mrr": false,
        "numeroConvocatoria": "804745",
        "descripcion": "UNIVERSITAT JAUME I: INVESTIGACIÓN ONCOLOGIA Y DEPORTE 2024",
        "descripcionLeng": null,
        "fechaRecepcion": "2024-12-20T12:26:09+01:00",
        "nivel1": "DIPUTACIÓN PROV. DE CASTELLÓN",
        "nivel2": "DIPUTACIÓN PROVINCIAL DE CASTELLÓ/CASTELLÓN",
        "nivel3": null,
        "codigoInvente": null
    },
    {
        "id": 1006304,
        "mrr": false,
        "numeroConvocatoria": "804744",
        "descripcion": "Resolución de 20 de diciembre de 2024, del Servicio Público de Empleo de Castilla y León, por la que se convocan becas y ayudas para personas desempleadas que participen en la oferta formativa prevista en la Orden EFP/942/2022, de 23 de septiembre",
        "descripcionLeng": null,
        "fechaRecepcion": "2024-12-20T12:24:03+01:00",
        "nivel1": "CASTILLA Y LEÓN",
        "nivel2": "SERVICIO PÚBLICO DE EMPLEO DE CASTILLA Y LEÓN",
        "nivel3": null,
        "codigoInvente": null
    }
]